pkging/__init__.py
pkging/main.py
pkging-0.1.0.dist-info/licenses/LICENSE
pkging-0.1.0.dist-info/METADATA
pkging-0.1.0.dist-info/WHEEL
pkging-0.1.0.dist-info/entry_points.txt
pkging-0.1.0.dist-info/top_level.txt
pkging-0.1.0.dist-info/RECORD
