Metadata-Version: 2.4
Name: pkging
Version: 0.1.0
Summary: Build a single executable file of your Python program.
Author-email: Juliano Fernandes <julianofernandes@gmail.com>
Project-URL: Repository, https://github.com/julianolf/pkging
Keywords: python,packaging,tools
Classifier: Programming Language :: Python :: 3 :: Only
Requires-Python: >=3.9
License-File: LICENSE
Requires-Dist: tomli; python_version < "3.11"
Dynamic: license-file
